tornadoql/__init__.py
tornadoql/graphql_handler.py
tornadoql/subscription_handler.py
tornadoql/tornadoql.py
tornadoql/static/graphiql.html
tornadoql-0.1.8.dist-info/LICENSE
tornadoql-0.1.8.dist-info/METADATA
tornadoql-0.1.8.dist-info/WHEEL
tornadoql-0.1.8.dist-info/entry_points.txt
tornadoql-0.1.8.dist-info/top_level.txt
tornadoql-0.1.8.dist-info/RECORD
