Metadata-Version: 2.1
Name: tornadoql
Version: 0.1.8
Summary: GraphQL API for dev and hosting using Graphene and Tornado
Home-page: https://github.com/deep-compute/tornadoql
Author: deep-compute
Author-email: support@deepcompute.com
License: MIT
Keywords: graphql,graphene,python,tornado
Platform: UNKNOWN
Classifier: Development Status :: 3 - Alpha
Classifier: Intended Audience :: Developers
Classifier: License :: OSI Approved :: MIT License
Classifier: Programming Language :: Python :: 3.4
Requires-Dist: basescript (==0.2.8)
Requires-Dist: graphene (==2.1.3)
Requires-Dist: tornado (>=5.1.1)
Requires-Dist: deeputil (==0.2.5)
Requires-Dist: Rx (==1.6.1)
